azure/messaging/webpubsubservice/__init__.py
azure/messaging/webpubsubservice/_client.py
azure/messaging/webpubsubservice/_configuration.py
azure/messaging/webpubsubservice/_models.py
azure/messaging/webpubsubservice/_patch.py
azure/messaging/webpubsubservice/_serialization.py
azure/messaging/webpubsubservice/_vendor.py
azure/messaging/webpubsubservice/_version.py
azure/messaging/webpubsubservice/py.typed
azure/messaging/webpubsubservice/_operations/__init__.py
azure/messaging/webpubsubservice/_operations/_operations.py
azure/messaging/webpubsubservice/_operations/_patch.py
azure/messaging/webpubsubservice/_utils/__init__.py
azure/messaging/webpubsubservice/_utils/serialization.py
azure/messaging/webpubsubservice/_utils/utils.py
azure/messaging/webpubsubservice/aio/__init__.py
azure/messaging/webpubsubservice/aio/_client.py
azure/messaging/webpubsubservice/aio/_configuration.py
azure/messaging/webpubsubservice/aio/_patch.py
azure/messaging/webpubsubservice/aio/_vendor.py
azure/messaging/webpubsubservice/aio/_operations/__init__.py
azure/messaging/webpubsubservice/aio/_operations/_operations.py
azure/messaging/webpubsubservice/aio/_operations/_patch.py
azure_messaging_webpubsubservice-1.3.0.dist-info/LICENSE
azure_messaging_webpubsubservice-1.3.0.dist-info/METADATA
azure_messaging_webpubsubservice-1.3.0.dist-info/WHEEL
azure_messaging_webpubsubservice-1.3.0.dist-info/top_level.txt
azure_messaging_webpubsubservice-1.3.0.dist-info/RECORD
